tgedr/__init__.py
tgedr/nihao/__init__.py
tgedr/nihao/assorted/chainable.py
tgedr/nihao/assorted/fetchers/__init__.py
tgedr/nihao/assorted/fetchers/fetcher_study.py
tgedr/nihao/assorted/fetchers/tickers_to_s3_parquet.py
tgedr/nihao/assorted/s3/__init__.py
tgedr/nihao/assorted/s3/s3_connector.py
tgedr/nihao/assorted/transformers/test.py
tgedr/nihao/assorted/transformers/transformer.py
tgedr/nihao/commons/__init__.py
tgedr/nihao/commons/chain.py
tgedr/nihao/commons/processor.py
tgedr/nihao/commons/sink.py
tgedr/nihao/commons/source.py
tgedr/nihao/impls/__init__.py
tgedr/nihao/impls/processors/__init__.py
tgedr/nihao/impls/processors/ticker_simple_analysis.py
tgedr/nihao/impls/sinks/__init__.py
tgedr/nihao/impls/sinks/s3.py
tgedr/nihao/impls/sources/__init__.py
tgedr/nihao/impls/sources/s3.py
tgedr/nihao/impls/sources/yahoo_tickers.py
tgedr_nihao-0.0.17.dist-info/LICENSE
tgedr_nihao-0.0.17.dist-info/METADATA
tgedr_nihao-0.0.17.dist-info/WHEEL
tgedr_nihao-0.0.17.dist-info/top_level.txt
tgedr_nihao-0.0.17.dist-info/RECORD
